cyint_aws_ml_ops_tools/glue/feature_store.py
cyint_aws_ml_ops_tools/glue/jobs.py
cyint_aws_ml_ops_tools-1.3.4.dist-info/LICENSE
cyint_aws_ml_ops_tools-1.3.4.dist-info/WHEEL
cyint_aws_ml_ops_tools-1.3.4.dist-info/METADATA
cyint_aws_ml_ops_tools-1.3.4.dist-info/RECORD
